{
  "db_name": "PostgreSQL",
  "query": "INSERT INTO organization_invites\n               (id, organization_id, email, role, token_hash, invited_by, expires_at)\n               VALUES ($1, $2, $3, $4, $5, $6, $7)",
  "describe": {
    "columns": [],
    "parameters": {
      "Left": [
        "Uuid",
        "Uuid",
        "Text",
        "Text",
        "Text",
        "Uuid",
        "Timestamptz"
      ]
    },
    "nullable": []
  },
  "hash": "5bba3a91287006d65af3ffa875532984c37b16fee891de4a6188dbbdf090ee80"
}
