{
  "db_name": "SQLite",
  "query": "SELECT workspace_id, principal_id, role as \"role: String\", created_at\n             FROM workspace_permissions WHERE principal_id = $1",
  "describe": {
    "columns": [
      {
        "name": "workspace_id",
        "ordinal": 0,
        "type_info": "Text"
      },
      {
        "name": "principal_id",
        "ordinal": 1,
        "type_info": "Text"
      },
      {
        "name": "role: String",
        "ordinal": 2,
        "type_info": "Text"
      },
      {
        "name": "created_at",
        "ordinal": 3,
        "type_info": "Text"
      }
    ],
    "parameters": {
      "Right": 1
    },
    "nullable": [
      false,
      false,
      false,
      false
    ]
  },
  "hash": "596173ece77dea6dc43ce25b23db91273635a48007df7aacf53cef9983aa0f72"
}
